AUTHORS.md
LICENSE
MANIFEST.in
README.md
requirements-dev.txt
requirements.txt
setup.cfg
setup.py
tox.ini
jorgemarcial_moto.egg-info/PKG-INFO
jorgemarcial_moto.egg-info/SOURCES.txt
jorgemarcial_moto.egg-info/dependency_links.txt
jorgemarcial_moto.egg-info/entry_points.txt
jorgemarcial_moto.egg-info/requires.txt
jorgemarcial_moto.egg-info/top_level.txt
moto/__init__.py
moto/backends.py
moto/compat.py
moto/server.py
moto/settings.py
moto/acm/__init__.py
moto/acm/models.py
moto/acm/responses.py
moto/acm/urls.py
moto/acm/utils.py
moto/apigateway/__init__.py
moto/apigateway/exceptions.py
moto/apigateway/models.py
moto/apigateway/responses.py
moto/apigateway/urls.py
moto/apigateway/utils.py
moto/autoscaling/__init__.py
moto/autoscaling/exceptions.py
moto/autoscaling/models.py
moto/autoscaling/responses.py
moto/autoscaling/urls.py
moto/awslambda/__init__.py
moto/awslambda/models.py
moto/awslambda/responses.py
moto/awslambda/urls.py
moto/cloudformation/__init__.py
moto/cloudformation/exceptions.py
moto/cloudformation/models.py
moto/cloudformation/parsing.py
moto/cloudformation/responses.py
moto/cloudformation/urls.py
moto/cloudformation/utils.py
moto/cloudwatch/__init__.py
moto/cloudwatch/models.py
moto/cloudwatch/responses.py
moto/cloudwatch/urls.py
moto/cloudwatch/utils.py
moto/core/__init__.py
moto/core/exceptions.py
moto/core/models.py
moto/core/responses.py
moto/core/urls.py
moto/core/utils.py
moto/datapipeline/__init__.py
moto/datapipeline/models.py
moto/datapipeline/responses.py
moto/datapipeline/urls.py
moto/datapipeline/utils.py
moto/dynamodb/__init__.py
moto/dynamodb/comparisons.py
moto/dynamodb/models.py
moto/dynamodb/responses.py
moto/dynamodb/urls.py
moto/dynamodb2/__init__.py
moto/dynamodb2/comparisons.py
moto/dynamodb2/models.py
moto/dynamodb2/responses.py
moto/dynamodb2/urls.py
moto/ec2/__init__.py
moto/ec2/exceptions.py
moto/ec2/models.py
moto/ec2/urls.py
moto/ec2/utils.py
moto/ec2/resources/instance_types.json
moto/ec2/responses/__init__.py
moto/ec2/responses/account_attributes.py
moto/ec2/responses/amazon_dev_pay.py
moto/ec2/responses/amis.py
moto/ec2/responses/availability_zones_and_regions.py
moto/ec2/responses/customer_gateways.py
moto/ec2/responses/dhcp_options.py
