Metadata-Version: 1.1
Name: jorgemarcial-moto
Version: 1.1.24
Summary: A library that allows your python tests to easily mock out the boto library
Home-page: https://github.com/jorgemarcial/moto
Author: Steve Pulec
Author-email: spulec@gmail.com
License: Apache
Platform: UNKNOWN
Classifier: Programming Language :: Python :: 2
Classifier: Programming Language :: Python :: 2.7
Classifier: Programming Language :: Python :: 3
Classifier: Programming Language :: Python :: 3.3
Classifier: Programming Language :: Python :: 3.4
Classifier: Programming Language :: Python :: 3.5
Classifier: Programming Language :: Python :: 3.6
Classifier: License :: OSI Approved :: Apache Software License
Classifier: Topic :: Software Development :: Testing
